{
"type": "FeatureCollection",
"name": "sql_statement",
"crs": { "type": "name", "properties": { "name": "urn:ogc:def:crs:OGC:1.3:CRS84" } },
"features": [
{ "type": "Feature", "properties": { "name": "Arthouse at the Jones Center", "tourism": "museum", "addr:state": null, "ele": null, "addr:housenumber": null, "addr:street": null, "wikidata": null, "addr:city": null, "addr:postcode": null, "opening_hours": null, "website": null, "phone": null, "description": null, "email": null, "operator": null }, "geometry": { "type": "Point", "coordinates": [ -97.7425732, 30.2692293 ] } },
{ "type": "Feature", "properties": { "name": "Charles Moore House", "tourism": "museum", "addr:state": null, "ele": null, "addr:housenumber": "2102", "addr:street": "Quarry", "wikidata": null, "addr:city": "Austin", "addr:postcode": "78703", "opening_hours": null, "website": null, "phone": null, "description": null, "email": null, "operator": null }, "geometry": { "type": "Point", "coordinates": [ -97.7665356, 30.2850537 ] } },
{ "type": "Feature", "properties": { "name": "Daughters of the Republic of Texas Museum", "tourism": "museum", "addr:state": "TX", "ele": "207", "addr:housenumber": null, "addr:street": null, "wikidata": null, "addr:city": null, "addr:postcode": null, "opening_hours": null, "website": null, "phone": null, "description": null, "email": null, "operator": null }, "geometry": { "type": "Point", "coordinates": [ -97.7016697, 30.3412592 ] } }
]
}
